{
    "name": "be",
    "date_order": "DMY",
    "january": [
        "студзень",
        "сту",
        "с",
        "студзеня"
    ],
    "february": [
        "люты",
        "лют",
        "л",
        "лютага"
    ],
    "march": [
        "сакавік",
        "сак",
        "с",
        "сакавіка"
    ],
    "april": [
        "красавік",
        "кра",
        "к",
        "красавіка"
    ],
    "may": [
        "май",
        "м",
        "мая"
    ],
    "june": [
        "чэрвень",
        "чэр",
        "ч",
        "чэрвеня"
    ],
    "july": [
        "ліпень",
        "ліп",
        "л",
        "ліпеня"
    ],
    "august": [
        "жнівень",
        "жні",
        "ж",
        "жніўня"
    ],
    "september": [
        "верасень",
        "вер",
        "в",
        "верасня"
    ],
    "october": [
        "кастрычнік",
        "кас",
        "к",
        "кастрычніка"
    ],
    "november": [
        "лістапад",
        "ліс",
        "л",
        "лістапада"
    ],
    "december": [
        "снежань",
        "сне",
        "с",
        "снежня"
    ],
    "monday": [
        "панядзелак",
        "пн",
        "п"
    ],
    "tuesday": [
        "аўторак",
        "аў",
        "а"
    ],
    "wednesday": [
        "серада",
        "ср",
        "с"
    ],
    "thursday": [
        "чацвер",
        "чц",
        "ч"
    ],
    "friday": [
        "пятніца",
        "пт",
        "п"
    ],
    "saturday": [
        "субота",
        "сб",
        "с"
    ],
    "sunday": [
        "нядзеля",
        "нд",
        "н"
    ],
    "am": [
        "am"
    ],
    "pm": [
        "pm"
    ],
    "year": [
        "год",
        "г"
    ],
    "month": [
        "месяц",
        "мес"
    ],
    "week": [
        "тыд"
    ],
    "day": [
        "дзень",
        "д"
    ],
    "hour": [
        "гадзіна",
        "гадз"
    ],
    "minute": [
        "хвіліна",
        "хв"
    ],
    "second": [
        "секунда",
        "с"
    ],
    "relative-type": {
        "1 year ago": [
            "у мінулым годзе"
        ],
        "0 year ago": [
            "у гэтым годзе"
        ],
        "in 1 year": [
            "у наступным годзе"
        ],
        "1 month ago": [
            "у мінулым месяцы"
        ],
        "0 month ago": [
            "у гэтым месяцы"
        ],
        "in 1 month": [
            "у наступным месяцы"
        ],
        "1 week ago": [
            "на мінулым тыдні"
        ],
        "0 week ago": [
            "на гэтым тыдні"
        ],
        "in 1 week": [
            "на наступным тыдні"
        ],
        "1 day ago": [
            "учора"
        ],
        "0 day ago": [
            "сёння"
        ],
        "in 1 day": [
            "заўтра"
        ],
        "0 hour ago": [
            "у гэту гадзіну"
        ],
        "0 minute ago": [
            "у гэту хвіліну"
        ],
        "0 second ago": [
            "цяпер"
        ],
        "in \\1 year": [
            "праз (\\d+) год",
            "праз (\\d+) года",
            "праз (\\d+) г"
        ],
        "\\1 year ago": [
            "(\\d+) год таму",
            "(\\d+) года таму",
            "(\\d+) г таму"
        ],
        "in \\1 month": [
            "праз (\\d+) месяц",
            "праз (\\d+) месяца",
            "праз (\\d+) мес"
        ],
        "\\1 month ago": [
            "(\\d+) месяц таму",
            "(\\d+) месяца таму",
            "(\\d+) мес таму"
        ],
        "in \\1 week": [
            "праз (\\d+) тыдзень",
            "праз (\\d+) тыдня",
            "праз (\\d+) тыд"
        ],
        "\\1 week ago": [
            "(\\d+) тыдзень таму",
            "(\\d+) тыдня таму",
            "(\\d+) тыд таму"
        ],
        "in \\1 day": [
            "праз (\\d+) дзень",
            "праз (\\d+) дня",
            "праз (\\d+) д"
        ],
        "\\1 day ago": [
            "(\\d+) дзень таму",
            "(\\d+) дня таму",
            "(\\d+) д таму"
        ],
        "in \\1 hour": [
            "праз (\\d+) гадзіну",
            "праз (\\d+) гадзіны",
            "праз (\\d+) гадз"
        ],
        "\\1 hour ago": [
            "(\\d+) гадзіну таму",
            "(\\d+) гадзіны таму",
            "(\\d+) гадз таму"
        ],
        "in \\1 minute": [
            "праз (\\d+) хвіліну",
            "праз (\\d+) хвіліны",
            "праз (\\d+) хв"
        ],
        "\\1 minute ago": [
            "(\\d+) хвіліну таму",
            "(\\d+) хвіліны таму",
            "(\\d+) хв таму"
        ],
        "in \\1 second": [
            "праз (\\d+) секунду",
            "праз (\\d+) секунды",
            "праз (\\d+) с"
        ],
        "\\1 second ago": [
            "(\\d+) секунду таму",
            "(\\d+) секунды таму",
            "(\\d+) с таму"
        ]
    },
    "locale_specific": {}
}