{
    "name": "jmc", 
    "date_order": "DMY", 
    "january": [
        "jan", 
        "januari", 
        "j"
    ], 
    "february": [
        "februari", 
        "feb", 
        "f"
    ], 
    "march": [
        "mac", 
        "m", 
        "machi"
    ], 
    "april": [
        "apr", 
        "aprilyi", 
        "a"
    ], 
    "may": [
        "m", 
        "mei"
    ], 
    "june": [
        "junyi", 
        "j", 
        "jun"
    ], 
    "july": [
        "j", 
        "jul", 
        "julyai"
    ], 
    "august": [
        "ago", 
        "a", 
        "agusti"
    ], 
    "september": [
        "s", 
        "septemba", 
        "sep"
    ], 
    "october": [
        "oktoba", 
        "okt", 
        "o"
    ], 
    "november": [
        "nov", 
        "novemba", 
        "n"
    ], 
    "december": [
        "desemba", 
        "des", 
        "d"
    ], 
    "monday": [
        "jtt", 
        "j", 
        "jumatatuu"
    ], 
    "tuesday": [
        "j", 
        "jumanne", 
        "jnn"
    ], 
    "wednesday": [
        "jtn", 
        "j", 
        "jumatanu"
    ], 
    "thursday": [
        "a", 
        "alhamisi", 
        "alh"
    ], 
    "friday": [
        "i", 
        "ijumaa", 
        "iju"
    ], 
    "saturday": [
        "jumamosi", 
        "j", 
        "jmo"
    ], 
    "sunday": [
        "jpi", 
        "jumapilyi", 
        "j"
    ], 
    "am": [
        "utuko"
    ], 
    "pm": [
        "kyiukonyi"
    ], 
    "year": [
        "maka"
    ], 
    "month": [
        "mori"
    ], 
    "week": [
        "wiikyi"
    ], 
    "day": [
        "mfiri"
    ], 
    "hour": [
        "saa"
    ], 
    "minute": [
        "dakyika"
    ], 
    "second": [
        "sekunde"
    ], 
    "relative-type": {
        "1 year ago": [
            "last year"
        ], 
        "0 year ago": [
            "this year"
        ], 
        "in 1 year": [
            "next year"
        ], 
        "1 month ago": [
            "last month"
        ], 
        "0 month ago": [
            "this month"
        ], 
        "in 1 month": [
            "next month"
        ], 
        "1 week ago": [
            "last week"
        ], 
        "0 week ago": [
            "this week"
        ], 
        "in 1 week": [
            "next week"
        ], 
        "1 day ago": [
            "ukou"
        ], 
        "0 day ago": [
            "inu"
        ], 
        "in 1 day": [
            "ngama"
        ], 
        "0 hour ago": [
            "this hour"
        ], 
        "0 minute ago": [
            "this minute"
        ], 
        "0 second ago": [
            "now"
        ], 
        "in \\1 year": [
            "+(\\d+) y"
        ], 
        "\\1 year ago": [
            "-(\\d+) y"
        ], 
        "in \\1 month": [
            "+(\\d+) m"
        ], 
        "\\1 month ago": [
            "-(\\d+) m"
        ], 
        "in \\1 week": [
            "+(\\d+) w"
        ], 
        "\\1 week ago": [
            "-(\\d+) w"
        ], 
        "in \\1 day": [
            "+(\\d+) d"
        ], 
        "\\1 day ago": [
            "-(\\d+) d"
        ], 
        "in \\1 hour": [
            "+(\\d+) h"
        ], 
        "\\1 hour ago": [
            "-(\\d+) h"
        ], 
        "in \\1 minute": [
            "+(\\d+) min"
        ], 
        "\\1 minute ago": [
            "-(\\d+) min"
        ], 
        "in \\1 second": [
            "+(\\d+) s"
        ], 
        "\\1 second ago": [
            "-(\\d+) s"
        ]
    }, 
    "locale_specific": {}
}