{
    "name": "mn", 
    "date_order": "YMD", 
    "january": [
        "1", 
        "Нэгдүгээр сар", 
        "1-р сар"
    ], 
    "february": [
        "2", 
        "2-р сар", 
        "Хоёрдугаар сар"
    ], 
    "march": [
        "Гуравдугаар сар", 
        "3-р сар", 
        "3"
    ], 
    "april": [
        "Дөрөвдүгээр сар", 
        "4-р сар", 
        "4"
    ], 
    "may": [
        "5-р сар", 
        "5", 
        "Тавдугаар сар"
    ], 
    "june": [
        "6", 
        "6-р сар", 
        "Зургадугаар сар"
    ], 
    "july": [
        "Долдугаар сар", 
        "7", 
        "7-р сар"
    ], 
    "august": [
        "8-р сар", 
        "Наймдугаар сар", 
        "8"
    ], 
    "september": [
        "9", 
        "9-р сар", 
        "Есдүгээр сар"
    ], 
    "october": [
        "10", 
        "Аравдугаар сар", 
        "10-р сар"
    ], 
    "november": [
        "11-р сар", 
        "11", 
        "Арван нэгдүгээр сар"
    ], 
    "december": [
        "Арван хоёрдугаар сар", 
        "12", 
        "12-р сар"
    ], 
    "monday": [
        "даваа", 
        "Да"
    ], 
    "tuesday": [
        "Мя", 
        "мягмар"
    ], 
    "wednesday": [
        "лхагва", 
        "Лх"
    ], 
    "thursday": [
        "Пү", 
        "пүрэв"
    ], 
    "friday": [
        "баасан", 
        "Ба"
    ], 
    "saturday": [
        "Бя", 
        "бямба"
    ], 
    "sunday": [
        "Ня", 
        "ням"
    ], 
    "am": [
        "ҮӨ", 
        "ү.ө", 
        "үө"
    ], 
    "pm": [
        "үх", 
        "ҮХ", 
        "ү.х"
    ], 
    "year": [
        "жил"
    ], 
    "month": [
        "сар"
    ], 
    "week": [
        "долоо хоног", 
        "7х"
    ], 
    "day": [
        "өдөр"
    ], 
    "hour": [
        "ц.", 
        "цаг"
    ], 
    "minute": [
        "мин.", 
        "минут"
    ], 
    "second": [
        "сек.", 
        "секунд"
    ], 
    "relative-type": {
        "1 year ago": [
            "өнгөрсөн жил"
        ], 
        "0 year ago": [
            "энэ жил"
        ], 
        "in 1 year": [
            "ирэх жил"
        ], 
        "1 month ago": [
            "өнгөрсөн сар"
        ], 
        "0 month ago": [
            "энэ сар"
        ], 
        "in 1 month": [
            "ирэх сар"
        ], 
        "1 week ago": [
            "өнгөрсөн долоо хоног"
        ], 
        "0 week ago": [
            "энэ долоо хоног"
        ], 
        "in 1 week": [
            "ирэх долоо хоног"
        ], 
        "1 day ago": [
            "өчигдөр"
        ], 
        "0 day ago": [
            "өнөөдөр"
        ], 
        "in 1 day": [
            "маргааш"
        ], 
        "0 hour ago": [
            "энэ цаг"
        ], 
        "0 minute ago": [
            "энэ минут"
        ], 
        "0 second ago": [
            "одоо"
        ], 
        "in \\1 year": [
            "+(\\d+) жилд", 
            "(\\d+) жилийн дараа"
        ], 
        "\\1 year ago": [
            "-(\\d+) жил.н өмнө", 
            "(\\d+) жилийн өмнө"
        ], 
        "in \\1 month": [
            "(\\d+) сарын дараа", 
            "+(\\d+) сард"
        ], 
        "\\1 month ago": [
            "(\\d+) сарын өмнө"
        ], 
        "in \\1 week": [
            "(\\d+) 7х-ийн дараа"
        ], 
        "\\1 week ago": [
            "(\\d+) 7х-ийн өмнө"
        ], 
        "in \\1 day": [
            "(\\d+) өдөрт", 
            "(\\d+) өдрийн дараа"
        ], 
        "\\1 day ago": [
            "(\\d+) өдрийн өмнө"
        ], 
        "in \\1 hour": [
            "(\\d+) ц. дараа", 
            "(\\d+) цагийн дараа"
        ], 
        "\\1 hour ago": [
            "(\\d+) ц. өмнө", 
            "(\\d+) цагийн өмнө"
        ], 
        "in \\1 minute": [
            "(\\d+) мин. дараа", 
            "(\\d+) минутын дараа"
        ], 
        "\\1 minute ago": [
            "(\\d+) мин. өмнө", 
            "(\\d+) минутын өмнө"
        ], 
        "in \\1 second": [
            "(\\d+) сек. дараа", 
            "(\\d+) секундын дараа"
        ], 
        "\\1 second ago": [
            "(\\d+) сек. өмнө", 
            "(\\d+) секундын өмнө"
        ]
    }, 
    "locale_specific": {}
}