{
    "name": "th", 
    "date_order": "DMY", 
    "january": [
        "ม.ค.", 
        "มกราคม"
    ], 
    "february": [
        "ก.พ.", 
        "กุมภาพันธ์"
    ], 
    "march": [
        "มีนาคม", 
        "มี.ค."
    ], 
    "april": [
        "เม.ย.", 
        "เมษายน"
    ], 
    "may": [
        "พ.ค.", 
        "พฤษภาคม"
    ], 
    "june": [
        "มิ.ย.", 
        "มิถุนายน"
    ], 
    "july": [
        "ก.ค.", 
        "กรกฎาคม"
    ], 
    "august": [
        "สิงหาคม", 
        "ส.ค."
    ], 
    "september": [
        "กันยายน", 
        "ก.ย."
    ], 
    "october": [
        "ตุลาคม", 
        "ต.ค."
    ], 
    "november": [
        "พ.ย.", 
        "พฤศจิกายน"
    ], 
    "december": [
        "ธ.ค.", 
        "ธันวาคม"
    ], 
    "monday": [
        "จ.", 
        "วันจันทร์", 
        "จ"
    ], 
    "tuesday": [
        "อ.", 
        "อ", 
        "วันอังคาร"
    ], 
    "wednesday": [
        "พ", 
        "พ.", 
        "วันพุธ"
    ], 
    "thursday": [
        "วันพฤหัสบดี", 
        "พฤ", 
        "พฤ."
    ], 
    "friday": [
        "ศ", 
        "ศ.", 
        "วันศุกร์"
    ], 
    "saturday": [
        "ส.", 
        "ส", 
        "วันเสาร์"
    ], 
    "sunday": [
        "วันอาทิตย์", 
        "อา.", 
        "อา"
    ], 
    "am": [
        "a", 
        "ก่อนเที่ยง"
    ], 
    "pm": [
        "p", 
        "หลังเที่ยง"
    ], 
    "year": [
        "ปี"
    ], 
    "month": [
        "เดือน"
    ], 
    "week": [
        "สัปดาห์"
    ], 
    "day": [
        "วัน"
    ], 
    "hour": [
        "ชม.", 
        "ชั่วโมง"
    ], 
    "minute": [
        "นาที", 
        "น."
    ], 
    "second": [
        "วินาที", 
        "วิ"
    ], 
    "relative-type": {
        "1 year ago": [
            "ปีที่แล้ว"
        ], 
        "0 year ago": [
            "ปีนี้"
        ], 
        "in 1 year": [
            "ปีหน้า"
        ], 
        "1 month ago": [
            "เดือนที่แล้ว"
        ], 
        "0 month ago": [
            "เดือนนี้"
        ], 
        "in 1 month": [
            "เดือนหน้า"
        ], 
        "1 week ago": [
            "สัปดาห์ที่แล้ว"
        ], 
        "0 week ago": [
            "สัปดาห์นี้"
        ], 
        "in 1 week": [
            "สัปดาห์หน้า"
        ], 
        "1 day ago": [
            "เมื่อวาน"
        ], 
        "0 day ago": [
            "วันนี้"
        ], 
        "in 1 day": [
            "พรุ่งนี้"
        ], 
        "0 hour ago": [
            "ชั่วโมงนี้"
        ], 
        "0 minute ago": [
            "นาทีนี้"
        ], 
        "0 second ago": [
            "ขณะนี้"
        ], 
        "in \\1 year": [
            "ในอีก (\\d+) ปี", 
            "ใน (\\d+) ปี"
        ], 
        "\\1 year ago": [
            "(\\d+) ปีที่แล้ว"
        ], 
        "in \\1 month": [
            "ใน (\\d+) เดือน", 
            "ในอีก (\\d+) เดือน"
        ], 
        "\\1 month ago": [
            "(\\d+) เดือนที่แล้ว", 
            "(\\d+) เดือนที่ผ่านมา"
        ], 
        "in \\1 week": [
            "ในอีก (\\d+) สัปดาห์", 
            "ใน (\\d+) สัปดาห์"
        ], 
        "\\1 week ago": [
            "(\\d+) สัปดาห์ที่แล้ว", 
            "(\\d+) สัปดาห์ที่ผ่านมา"
        ], 
        "in \\1 day": [
            "ในอีก (\\d+) วัน", 
            "ใน (\\d+) วัน"
        ], 
        "\\1 day ago": [
            "(\\d+) วันที่แล้ว", 
            "(\\d+) วันที่ผ่านมา"
        ], 
        "in \\1 hour": [
            "ในอีก (\\d+) ชั่วโมง", 
            "ใน (\\d+) ชม."
        ], 
        "\\1 hour ago": [
            "(\\d+) ชม. ที่แล้ว", 
            "(\\d+) ชั่วโมงที่ผ่านมา"
        ], 
        "in \\1 minute": [
            "ในอีก (\\d+) นาที", 
            "ใน (\\d+) นาที"
        ], 
        "\\1 minute ago": [
            "(\\d+) นาทีที่แล้ว", 
            "(\\d+) นาทีที่ผ่านมา"
        ], 
        "in \\1 second": [
            "ในอีก (\\d+) วินาที", 
            "ใน (\\d+) วินาที"
        ], 
        "\\1 second ago": [
            "(\\d+) วินาทีที่แล้ว", 
            "(\\d+) วินาทีที่ผ่านมา"
        ]
    }, 
    "locale_specific": {}
}